uuid_forge/__init__.py
uuid_forge/_version.py
uuid_forge/cli.py
uuid_forge/config.py
uuid_forge/core.py
uuid_forge/py.typed
uuid_forge-0.1.1.dist-info/METADATA
uuid_forge-0.1.1.dist-info/WHEEL
uuid_forge-0.1.1.dist-info/entry_points.txt
uuid_forge-0.1.1.dist-info/RECORD
