Metadata-Version: 2.4
Name: uuid-forge
Version: 0.1.1
Summary: Deterministic UUID generation for cross-system coordination
Project-URL: Homepage, https://github.com/darth-veitcher/uuid-forge
Project-URL: Documentation, https://darth-veitcher.github.io/uuid-forge
Project-URL: Repository, https://github.com/darth-veitcher/uuid-forge
Project-URL: Issues, https://github.com/darth-veitcher/uuid-forge/issues
Author-email: darth-veitcher <1722315+darth-veitcher@users.noreply.github.com>
License: MIT
Keywords: coordination,deterministic,distributed-systems,idempotent,microservices,uuid
Classifier: Development Status :: 4 - Beta
Classifier: Intended Audience :: Developers
Classifier: License :: OSI Approved :: MIT License
Classifier: Operating System :: OS Independent
Classifier: Programming Language :: Python :: 3
Classifier: Programming Language :: Python :: 3.11
Classifier: Programming Language :: Python :: 3.12
Classifier: Programming Language :: Python :: 3.13
Classifier: Topic :: Software Development :: Libraries :: Python Modules
Classifier: Topic :: System :: Distributed Computing
Classifier: Typing :: Typed
Requires-Python: >=3.11
Requires-Dist: rich>=14.1.0
Requires-Dist: typer>=0.19.2
